forecastfactor_publisher/__init__.py
forecastfactor_publisher/publisher.py
forecastfactor_publisher-1.0.6.dist-info/METADATA
forecastfactor_publisher-1.0.6.dist-info/WHEEL
forecastfactor_publisher-1.0.6.dist-info/top_level.txt
forecastfactor_publisher-1.0.6.dist-info/RECORD
