Metadata-Version: 2.2
Name: forecastfactor_publisher
Version: 1.0.6
Summary: A library for publishing forecast data to an API
Author: Ricardo Teixeira
Author-email: ricardo.teixeira@obiio.com
Classifier: Programming Language :: Python :: 3
Classifier: License :: OSI Approved :: MIT License
Classifier: Operating System :: OS Independent
Requires-Python: >=3.7
Requires-Dist: requests
Requires-Dist: pandas
Dynamic: author
Dynamic: author-email
Dynamic: classifier
Dynamic: requires-dist
Dynamic: requires-python
Dynamic: summary
